trisigma/__init__.py
trisigma/alg_events.py
trisigma/alg_exceptions.py
trisigma/backtesting.py
trisigma/binance_stream.py
trisigma/cloud_storage.py
trisigma/evaluation_utils.py
trisigma/filemanager.py
trisigma/ibkr.py
trisigma/pots.py
trisigma/scraper.py
trisigma/sheets.py
trisigma/stream.py
trisigma/time_utils.py
trisigma/tuner.py
trisigma/yahoo.py
trisigma-1.0.0.dist-info/METADATA
trisigma-1.0.0.dist-info/WHEEL
trisigma-1.0.0.dist-info/top_level.txt
trisigma-1.0.0.dist-info/RECORD
