Metadata-Version: 2.1
Name: trisigma
Version: 1.0.0
Summary: trisigma engine
Author: Arda Gok
Author-email: ardagkmhs@gmail.com
Keywords: python,algo-trading,finance,stocks,crypto,market
Requires-Dist: numpy
Requires-Dist: pandas
Requires-Dist: binance-connector
Requires-Dist: requests
